README
setup.py
vipr_data_cli.egg-info/PKG-INFO
vipr_data_cli.egg-info/SOURCES.txt
vipr_data_cli.egg-info/dependency_links.txt
vipr_data_cli.egg-info/entry_points.txt
vipr_data_cli.egg-info/requires.txt
vipr_data_cli.egg-info/top_level.txt
viprdatacli/__init__.py
viprdatacli/fileaccess.py
viprdatacli/xml2obj.py
viprdatacli/scripts/__init__.py
viprdatacli/scripts/viprfileaccess.py
viprdatacli/scripts/viprmount.py
viprdatacli/scripts/viprumount.py