Metadata-Version: 1.1
Name: vipr-data-cli
Version: 0.5.1
Summary: EMC ViPR data-services: NFS mount scripts for object buckets
Home-page: https://community.emc.com/community/edn/vipr-data-services
Author: EMC
Author-email: ViPR.Data.Services.SDK@emc.com
License: BSD
Keywords: emc vipr dataservices nfs mount object bucket
Platform: UNKNOWN
Classifier: Development Status :: 4 - Beta
Classifier: Topic :: Utilities
Classifier: License :: OSI Approved :: BSD License
